{
  "1": [
    { "date": "2025-12-01", "quantity": 257, "partName": "Part D", "poNumber": "PO-0001" },
    { "date": "2025-12-01", "quantity": 205, "partName": "Part A", "poNumber": "PO-0001" },
    { "date": "2025-12-01", "quantity": 294, "partName": "Part B", "poNumber": "PO-0001" },
    { "date": "2025-12-01", "quantity": 233, "partName": "Part C", "poNumber": "PO-0002" },
    { "date": "2025-12-02", "quantity": 366, "partName": "Part B", "poNumber": "PO-0002" },
    { "date": "2025-12-02", "quantity": 178, "partName": "Part E", "poNumber": "PO-0002" },
    { "date": "2025-12-02", "quantity": 322, "partName": "Part D", "poNumber": "PO-0003" },
    { "date": "2025-12-02", "quantity": 358, "partName": "Part A", "poNumber": "PO-0003" },
    { "date": "2025-12-02", "quantity": 125, "partName": "Part C", "poNumber": "PO-0004" },
    { "date": "2025-12-03", "quantity": 219, "partName": "Part A", "poNumber": "PO-0004" },
    { "date": "2025-12-03", "quantity": 335, "partName": "Part D", "poNumber": "PO-0005" },
    { "date": "2025-12-03", "quantity": 152, "partName": "Part C", "poNumber": "PO-0005" },
    { "date": "2025-12-04", "quantity": 268, "partName": "Part D", "poNumber": "PO-0006" },
    { "date": "2025-12-04", "quantity": 250, "partName": "Part B", "poNumber": "PO-0007" },
    { "date": "2025-12-04", "quantity": 212, "partName": "Part E", "poNumber": "PO-0007" },
    { "date": "2025-12-05", "quantity": 335, "partName": "Part B", "poNumber": "PO-0008" },
    { "date": "2025-12-05", "quantity": 291, "partName": "Part C", "poNumber": "PO-0008" },
    { "date": "2025-12-05", "quantity": 358, "partName": "Part E", "poNumber": "PO-0009" },
    { "date": "2025-12-05", "quantity": 338, "partName": "Part A", "poNumber": "PO-0009" },
    { "date": "2025-12-06", "quantity": 305, "partName": "Part B", "poNumber": "PO-0010" },
    { "date": "2025-12-06", "quantity": 226, "partName": "Part D", "poNumber": "PO-0010" },
    { "date": "2025-12-06", "quantity": 147, "partName": "Part C", "poNumber": "PO-0011" },
    { "date": "2025-12-07", "quantity": 181, "partName": "Part B", "poNumber": "PO-0011" },
    { "date": "2025-12-07", "quantity": 77, "partName": "Part E", "poNumber": "PO-0012" },
    { "date": "2025-12-07", "quantity": 95, "partName": "Part A", "poNumber": "PO-0012" },
    { "date": "2025-12-08", "quantity": 294, "partName": "Part E", "poNumber": "PO-0013" },
    { "date": "2025-12-08", "quantity": 196, "partName": "Part C", "poNumber": "PO-0013" },
    { "date": "2025-12-09", "quantity": 231, "partName": "Part A", "poNumber": "PO-0014" },
    { "date": "2025-12-09", "quantity": 338, "partName": "Part D", "poNumber": "PO-0014" },
    { "date": "2025-12-09", "quantity": 290, "partName": "Part B", "poNumber": "PO-0015" },
    { "date": "2025-12-09", "quantity": 181, "partName": "Part E", "poNumber": "PO-0015" },
    { "date": "2025-12-10", "quantity": 310, "partName": "Part C", "poNumber": "PO-0016" },
    { "date": "2025-12-10", "quantity": 101, "partName": "Part A", "poNumber": "PO-0016" },
    { "date": "2025-12-11", "quantity": 246, "partName": "Part D", "poNumber": "PO-0017" },
    { "date": "2025-12-11", "quantity": 194, "partName": "Part C", "poNumber": "PO-0018" },
    { "date": "2025-12-11", "quantity": 152, "partName": "Part B", "poNumber": "PO-0018" },
    { "date": "2025-12-12", "quantity": 102, "partName": "Part D", "poNumber": "PO-0019" },
    { "date": "2025-12-12", "quantity": 364, "partName": "Part E", "poNumber": "PO-0019" },
    { "date": "2025-12-12", "quantity": 318, "partName": "Part A", "poNumber": "PO-0020" },
    { "date": "2025-12-13", "quantity": 257, "partName": "Part A", "poNumber": "PO-0020" },
    { "date": "2025-12-13", "quantity": 392, "partName": "Part B", "poNumber": "PO-0021" },
    { "date": "2025-12-14", "quantity": 237, "partName": "Part C", "poNumber": "PO-0021" },
    { "date": "2025-12-14", "quantity": 346, "partName": "Part B", "poNumber": "PO-0022" },
    { "date": "2025-12-14", "quantity": 281, "partName": "Part D", "poNumber": "PO-0022" },
    { "date": "2025-12-14", "quantity": 267, "partName": "Part E", "poNumber": "PO-0023" },
    { "date": "2025-12-15", "quantity": 224, "partName": "Part A", "poNumber": "PO-0024" },
    { "date": "2025-12-16", "quantity": 334, "partName": "Part B", "poNumber": "PO-0024" },
    { "date": "2025-12-16", "quantity": 68, "partName": "Part D", "poNumber": "PO-0025" },
    { "date": "2025-12-16", "quantity": 205, "partName": "Part E", "poNumber": "PO-0025" },
    { "date": "2025-12-16", "quantity": 128, "partName": "Part C", "poNumber": "PO-0026" },
    { "date": "2025-12-17", "quantity": 314, "partName": "Part A", "poNumber": "PO-0026" },
    { "date": "2025-12-17", "quantity": 258, "partName": "Part D", "poNumber": "PO-0027" },
    { "date": "2025-12-18", "quantity": 269, "partName": "Part C", "poNumber": "PO-0028" },
    { "date": "2025-12-18", "quantity": 260, "partName": "Part E", "poNumber": "PO-0029" },
    { "date": "2025-12-18", "quantity": 235, "partName": "Part D", "poNumber": "PO-0030" },
    { "date": "2025-12-18", "quantity": 316, "partName": "Part B", "poNumber": "PO-0030" },
    { "date": "2025-12-19", "quantity": 85, "partName": "Part A", "poNumber": "PO-0031" },
    { "date": "2025-12-19", "quantity": 206, "partName": "Part C", "poNumber": "PO-0031" },
    { "date": "2025-12-19", "quantity": 171, "partName": "Part D", "poNumber": "PO-0032" }
  ],
  "2": [
    { "date": "2025-12-01", "quantity": 343, "partName": "Part D", "poNumber": "PO-0001" },
    { "date": "2025-12-01", "quantity": 244, "partName": "Part A", "poNumber": "PO-0001" },
    { "date": "2025-12-01", "quantity": 264, "partName": "Part B", "poNumber": "PO-0001" },
    { "date": "2025-12-01", "quantity": 233, "partName": "Part C", "poNumber": "PO-0002" },
    { "date": "2025-12-02", "quantity": 366, "partName": "Part B", "poNumber": "PO-0002" },
    { "date": "2025-12-02", "quantity": 178, "partName": "Part E", "poNumber": "PO-0002" },
    { "date": "2025-12-02", "quantity": 322, "partName": "Part D", "poNumber": "PO-0003" },
    { "date": "2025-12-02", "quantity": 358, "partName": "Part A", "poNumber": "PO-0003" },
    { "date": "2025-12-02", "quantity": 125, "partName": "Part C", "poNumber": "PO-0004" },
    { "date": "2025-12-03", "quantity": 219, "partName": "Part A", "poNumber": "PO-0004" },
    { "date": "2025-12-03", "quantity": 335, "partName": "Part D", "poNumber": "PO-0005" },
    { "date": "2025-12-03", "quantity": 152, "partName": "Part C", "poNumber": "PO-0005" },
    { "date": "2025-12-04", "quantity": 268, "partName": "Part D", "poNumber": "PO-0006" },
    { "date": "2025-12-04", "quantity": 250, "partName": "Part B", "poNumber": "PO-0007" },
    { "date": "2025-12-04", "quantity": 212, "partName": "Part E", "poNumber": "PO-0007" },
    { "date": "2025-12-05", "quantity": 335, "partName": "Part B", "poNumber": "PO-0008" },
    { "date": "2025-12-05", "quantity": 291, "partName": "Part C", "poNumber": "PO-0008" },
    { "date": "2025-12-05", "quantity": 358, "partName": "Part E", "poNumber": "PO-0009" },
    { "date": "2025-12-05", "quantity": 338, "partName": "Part A", "poNumber": "PO-0009" },
    { "date": "2025-12-06", "quantity": 305, "partName": "Part B", "poNumber": "PO-0010" },
    { "date": "2025-12-06", "quantity": 226, "partName": "Part D", "poNumber": "PO-0010" },
    { "date": "2025-12-06", "quantity": 147, "partName": "Part C", "poNumber": "PO-0011" },
    { "date": "2025-12-07", "quantity": 181, "partName": "Part B", "poNumber": "PO-0011" },
    { "date": "2025-12-07", "quantity": 77, "partName": "Part E", "poNumber": "PO-0012" },
    { "date": "2025-12-07", "quantity": 95, "partName": "Part A", "poNumber": "PO-0012" },
    { "date": "2025-12-08", "quantity": 294, "partName": "Part E", "poNumber": "PO-0013" },
    { "date": "2025-12-08", "quantity": 196, "partName": "Part C", "poNumber": "PO-0013" },
    { "date": "2025-12-09", "quantity": 231, "partName": "Part A", "poNumber": "PO-0014" },
    { "date": "2025-12-09", "quantity": 338, "partName": "Part D", "poNumber": "PO-0014" },
    { "date": "2025-12-09", "quantity": 290, "partName": "Part B", "poNumber": "PO-0015" },
    { "date": "2025-12-09", "quantity": 181, "partName": "Part E", "poNumber": "PO-0015" },
    { "date": "2025-12-10", "quantity": 310, "partName": "Part C", "poNumber": "PO-0016" },
    { "date": "2025-12-10", "quantity": 101, "partName": "Part A", "poNumber": "PO-0016" },
    { "date": "2025-12-11", "quantity": 246, "partName": "Part D", "poNumber": "PO-0017" },
    { "date": "2025-12-11", "quantity": 194, "partName": "Part C", "poNumber": "PO-0018" },
    { "date": "2025-12-11", "quantity": 152, "partName": "Part B", "poNumber": "PO-0018" },
    { "date": "2025-12-12", "quantity": 102, "partName": "Part D", "poNumber": "PO-0019" },
    { "date": "2025-12-12", "quantity": 364, "partName": "Part E", "poNumber": "PO-0019" },
    { "date": "2025-12-12", "quantity": 318, "partName": "Part A", "poNumber": "PO-0020" },
    { "date": "2025-12-13", "quantity": 257, "partName": "Part A", "poNumber": "PO-0020" },
    { "date": "2025-12-13", "quantity": 392, "partName": "Part B", "poNumber": "PO-0021" },
    { "date": "2025-12-14", "quantity": 237, "partName": "Part C", "poNumber": "PO-0021" },
    { "date": "2025-12-14", "quantity": 346, "partName": "Part B", "poNumber": "PO-0022" },
    { "date": "2025-12-14", "quantity": 281, "partName": "Part D", "poNumber": "PO-0022" },
    { "date": "2025-12-14", "quantity": 267, "partName": "Part E", "poNumber": "PO-0023" },
    { "date": "2025-12-15", "quantity": 224, "partName": "Part A", "poNumber": "PO-0024" },
    { "date": "2025-12-16", "quantity": 334, "partName": "Part B", "poNumber": "PO-0024" },
    { "date": "2025-12-16", "quantity": 68, "partName": "Part D", "poNumber": "PO-0025" },
    { "date": "2025-12-16", "quantity": 205, "partName": "Part E", "poNumber": "PO-0025" },
    { "date": "2025-12-16", "quantity": 128, "partName": "Part C", "poNumber": "PO-0026" },
    { "date": "2025-12-17", "quantity": 314, "partName": "Part A", "poNumber": "PO-0026" },
    { "date": "2025-12-17", "quantity": 258, "partName": "Part D", "poNumber": "PO-0027" },
    { "date": "2025-12-18", "quantity": 269, "partName": "Part C", "poNumber": "PO-0028" },
    { "date": "2025-12-18", "quantity": 260, "partName": "Part E", "poNumber": "PO-0029" },
    { "date": "2025-12-18", "quantity": 235, "partName": "Part D", "poNumber": "PO-0030" },
    { "date": "2025-12-18", "quantity": 316, "partName": "Part B", "poNumber": "PO-0030" },
    { "date": "2025-12-19", "quantity": 85, "partName": "Part A", "poNumber": "PO-0031" },
    { "date": "2025-12-19", "quantity": 206, "partName": "Part C", "poNumber": "PO-0031" },
    { "date": "2025-12-19", "quantity": 171, "partName": "Part D", "poNumber": "PO-0032" }
  ],
  "3": [
    { "date": "2025-12-01", "quantity": 343, "partName": "Part D", "poNumber": "PO-0001" },
    { "date": "2025-12-01", "quantity": 244, "partName": "Part A", "poNumber": "PO-0001" },
    { "date": "2025-12-01", "quantity": 264, "partName": "Part B", "poNumber": "PO-0001" },
    { "date": "2025-12-01", "quantity": 233, "partName": "Part C", "poNumber": "PO-0002" },
    { "date": "2025-12-02", "quantity": 366, "partName": "Part B", "poNumber": "PO-0002" },
    { "date": "2025-12-02", "quantity": 178, "partName": "Part E", "poNumber": "PO-0002" },
    { "date": "2025-12-02", "quantity": 322, "partName": "Part D", "poNumber": "PO-0003" },
    { "date": "2025-12-02", "quantity": 358, "partName": "Part A", "poNumber": "PO-0003" },
    { "date": "2025-12-02", "quantity": 125, "partName": "Part C", "poNumber": "PO-0004" },
    { "date": "2025-12-03", "quantity": 219, "partName": "Part A", "poNumber": "PO-0004" },
    { "date": "2025-12-03", "quantity": 335, "partName": "Part D", "poNumber": "PO-0005" },
    { "date": "2025-12-03", "quantity": 152, "partName": "Part C", "poNumber": "PO-0005" },
    { "date": "2025-12-04", "quantity": 268, "partName": "Part D", "poNumber": "PO-0006" },
    { "date": "2025-12-04", "quantity": 250, "partName": "Part B", "poNumber": "PO-0007" },
    { "date": "2025-12-04", "quantity": 212, "partName": "Part E", "poNumber": "PO-0007" },
    { "date": "2025-12-05", "quantity": 335, "partName": "Part B", "poNumber": "PO-0008" },
    { "date": "2025-12-05", "quantity": 291, "partName": "Part C", "poNumber": "PO-0008" },
    { "date": "2025-12-05", "quantity": 358, "partName": "Part E", "poNumber": "PO-0009" },
    { "date": "2025-12-05", "quantity": 338, "partName": "Part A", "poNumber": "PO-0009" },
    { "date": "2025-12-06", "quantity": 305, "partName": "Part B", "poNumber": "PO-0010" },
    { "date": "2025-12-06", "quantity": 226, "partName": "Part D", "poNumber": "PO-0010" },
    { "date": "2025-12-06", "quantity": 147, "partName": "Part C", "poNumber": "PO-0011" },
    { "date": "2025-12-07", "quantity": 181, "partName": "Part B", "poNumber": "PO-0011" },
    { "date": "2025-12-07", "quantity": 77, "partName": "Part E", "poNumber": "PO-0012" },
    { "date": "2025-12-07", "quantity": 95, "partName": "Part A", "poNumber": "PO-0012" },
    { "date": "2025-12-08", "quantity": 294, "partName": "Part E", "poNumber": "PO-0013" },
    { "date": "2025-12-08", "quantity": 196, "partName": "Part C", "poNumber": "PO-0013" },
    { "date": "2025-12-09", "quantity": 231, "partName": "Part A", "poNumber": "PO-0014" },
    { "date": "2025-12-09", "quantity": 338, "partName": "Part D", "poNumber": "PO-0014" },
    { "date": "2025-12-09", "quantity": 290, "partName": "Part B", "poNumber": "PO-0015" },
    { "date": "2025-12-09", "quantity": 181, "partName": "Part E", "poNumber": "PO-0015" },
    { "date": "2025-12-10", "quantity": 310, "partName": "Part C", "poNumber": "PO-0016" },
    { "date": "2025-12-10", "quantity": 101, "partName": "Part A", "poNumber": "PO-0016" },
    { "date": "2025-12-11", "quantity": 246, "partName": "Part D", "poNumber": "PO-0017" },
    { "date": "2025-12-11", "quantity": 194, "partName": "Part C", "poNumber": "PO-0018" },
    { "date": "2025-12-11", "quantity": 152, "partName": "Part B", "poNumber": "PO-0018" },
    { "date": "2025-12-12", "quantity": 102, "partName": "Part D", "poNumber": "PO-0019" },
    { "date": "2025-12-12", "quantity": 364, "partName": "Part E", "poNumber": "PO-0019" },
    { "date": "2025-12-12", "quantity": 318, "partName": "Part A", "poNumber": "PO-0020" },
    { "date": "2025-12-13", "quantity": 257, "partName": "Part A", "poNumber": "PO-0020" },
    { "date": "2025-12-13", "quantity": 392, "partName": "Part B", "poNumber": "PO-0021" },
    { "date": "2025-12-14", "quantity": 237, "partName": "Part C", "poNumber": "PO-0021" },
    { "date": "2025-12-14", "quantity": 346, "partName": "Part B", "poNumber": "PO-0022" },
    { "date": "2025-12-14", "quantity": 281, "partName": "Part D", "poNumber": "PO-0022" },
    { "date": "2025-12-14", "quantity": 267, "partName": "Part E", "poNumber": "PO-0023" },
    { "date": "2025-12-15", "quantity": 224, "partName": "Part A", "poNumber": "PO-0024" },
    { "date": "2025-12-16", "quantity": 334, "partName": "Part B", "poNumber": "PO-0024" },
    { "date": "2025-12-16", "quantity": 68, "partName": "Part D", "poNumber": "PO-0025" },
    { "date": "2025-12-16", "quantity": 205, "partName": "Part E", "poNumber": "PO-0025" },
    { "date": "2025-12-16", "quantity": 128, "partName": "Part C", "poNumber": "PO-0026" },
    { "date": "2025-12-17", "quantity": 314, "partName": "Part A", "poNumber": "PO-0026" },
    { "date": "2025-12-17", "quantity": 258, "partName": "Part D", "poNumber": "PO-0027" },
    { "date": "2025-12-18", "quantity": 269, "partName": "Part C", "poNumber": "PO-0028" },
    { "date": "2025-12-18", "quantity": 260, "partName": "Part E", "poNumber": "PO-0029" },
    { "date": "2025-12-18", "quantity": 235, "partName": "Part D", "poNumber": "PO-0030" },
    { "date": "2025-12-18", "quantity": 316, "partName": "Part B", "poNumber": "PO-0030" },
    { "date": "2025-12-19", "quantity": 85, "partName": "Part A", "poNumber": "PO-0031" },
    { "date": "2025-12-19", "quantity": 206, "partName": "Part C", "poNumber": "PO-0031" },
    { "date": "2025-12-19", "quantity": 171, "partName": "Part D", "poNumber": "PO-0032" }
  ],
  "4": [
    { "date": "2025-12-01", "quantity": 343, "partName": "Part D", "poNumber": "PO-0001" },
    { "date": "2025-12-01", "quantity": 244, "partName": "Part A", "poNumber": "PO-0001" },
    { "date": "2025-12-01", "quantity": 264, "partName": "Part B", "poNumber": "PO-0001" },
    { "date": "2025-12-01", "quantity": 233, "partName": "Part C", "poNumber": "PO-0002" },
    { "date": "2025-12-02", "quantity": 366, "partName": "Part B", "poNumber": "PO-0002" },
    { "date": "2025-12-02", "quantity": 178, "partName": "Part E", "poNumber": "PO-0002" },
    { "date": "2025-12-02", "quantity": 322, "partName": "Part D", "poNumber": "PO-0003" },
    { "date": "2025-12-02", "quantity": 358, "partName": "Part A", "poNumber": "PO-0003" },
    { "date": "2025-12-02", "quantity": 125, "partName": "Part C", "poNumber": "PO-0004" },
    { "date": "2025-12-03", "quantity": 219, "partName": "Part A", "poNumber": "PO-0004" },
    { "date": "2025-12-03", "quantity": 335, "partName": "Part D", "poNumber": "PO-0005" },
    { "date": "2025-12-03", "quantity": 152, "partName": "Part C", "poNumber": "PO-0005" },
    { "date": "2025-12-04", "quantity": 268, "partName": "Part D", "poNumber": "PO-0006" },
    { "date": "2025-12-04", "quantity": 250, "partName": "Part B", "poNumber": "PO-0007" },
    { "date": "2025-12-04", "quantity": 212, "partName": "Part E", "poNumber": "PO-0007" },
    { "date": "2025-12-05", "quantity": 335, "partName": "Part B", "poNumber": "PO-0008" },
    { "date": "2025-12-05", "quantity": 291, "partName": "Part C", "poNumber": "PO-0008" },
    { "date": "2025-12-05", "quantity": 358, "partName": "Part E", "poNumber": "PO-0009" },
    { "date": "2025-12-05", "quantity": 338, "partName": "Part A", "poNumber": "PO-0009" },
    { "date": "2025-12-06", "quantity": 305, "partName": "Part B", "poNumber": "PO-0010" },
    { "date": "2025-12-06", "quantity": 226, "partName": "Part D", "poNumber": "PO-0010" },
    { "date": "2025-12-06", "quantity": 147, "partName": "Part C", "poNumber": "PO-0011" },
    { "date": "2025-12-07", "quantity": 181, "partName": "Part B", "poNumber": "PO-0011" },
    { "date": "2025-12-07", "quantity": 77, "partName": "Part E", "poNumber": "PO-0012" },
    { "date": "2025-12-07", "quantity": 95, "partName": "Part A", "poNumber": "PO-0012" },
    { "date": "2025-12-08", "quantity": 294, "partName": "Part E", "poNumber": "PO-0013" },
    { "date": "2025-12-08", "quantity": 196, "partName": "Part C", "poNumber": "PO-0013" },
    { "date": "2025-12-09", "quantity": 231, "partName": "Part A", "poNumber": "PO-0014" },
    { "date": "2025-12-09", "quantity": 338, "partName": "Part D", "poNumber": "PO-0014" },
    { "date": "2025-12-09", "quantity": 290, "partName": "Part B", "poNumber": "PO-0015" },
    { "date": "2025-12-09", "quantity": 181, "partName": "Part E", "poNumber": "PO-0015" },
    { "date": "2025-12-10", "quantity": 310, "partName": "Part C", "poNumber": "PO-0016" },
    { "date": "2025-12-10", "quantity": 101, "partName": "Part A", "poNumber": "PO-0016" },
    { "date": "2025-12-11", "quantity": 246, "partName": "Part D", "poNumber": "PO-0017" },
    { "date": "2025-12-11", "quantity": 194, "partName": "Part C", "poNumber": "PO-0018" },
    { "date": "2025-12-11", "quantity": 152, "partName": "Part B", "poNumber": "PO-0018" },
    { "date": "2025-12-12", "quantity": 102, "partName": "Part D", "poNumber": "PO-0019" },
    { "date": "2025-12-12", "quantity": 364, "partName": "Part E", "poNumber": "PO-0019" },
    { "date": "2025-12-12", "quantity": 318, "partName": "Part A", "poNumber": "PO-0020" },
    { "date": "2025-12-13", "quantity": 257, "partName": "Part A", "poNumber": "PO-0020" },
    { "date": "2025-12-13", "quantity": 392, "partName": "Part B", "poNumber": "PO-0021" },
    { "date": "2025-12-14", "quantity": 237, "partName": "Part C", "poNumber": "PO-0021" },
    { "date": "2025-12-14", "quantity": 346, "partName": "Part B", "poNumber": "PO-0022" },
    { "date": "2025-12-14", "quantity": 281, "partName": "Part D", "poNumber": "PO-0022" },
    { "date": "2025-12-14", "quantity": 267, "partName": "Part E", "poNumber": "PO-0023" },
    { "date": "2025-12-15", "quantity": 224, "partName": "Part A", "poNumber": "PO-0024" },
    { "date": "2025-12-16", "quantity": 334, "partName": "Part B", "poNumber": "PO-0024" },
    { "date": "2025-12-16", "quantity": 68, "partName": "Part D", "poNumber": "PO-0025" },
    { "date": "2025-12-16", "quantity": 205, "partName": "Part E", "poNumber": "PO-0025" },
    { "date": "2025-12-16", "quantity": 128, "partName": "Part C", "poNumber": "PO-0026" },
    { "date": "2025-12-17", "quantity": 314, "partName": "Part A", "poNumber": "PO-0026" },
    { "date": "2025-12-17", "quantity": 258, "partName": "Part D", "poNumber": "PO-0027" },
    { "date": "2025-12-18", "quantity": 269, "partName": "Part C", "poNumber": "PO-0028" },
    { "date": "2025-12-18", "quantity": 260, "partName": "Part E", "poNumber": "PO-0029" },
    { "date": "2025-12-18", "quantity": 235, "partName": "Part D", "poNumber": "PO-0030" },
    { "date": "2025-12-18", "quantity": 316, "partName": "Part B", "poNumber": "PO-0030" },
    { "date": "2025-12-19", "quantity": 85, "partName": "Part A", "poNumber": "PO-0031" },
    { "date": "2025-12-19", "quantity": 206, "partName": "Part C", "poNumber": "PO-0031" },
    { "date": "2025-12-19", "quantity": 171, "partName": "Part D", "poNumber": "PO-0032" }
  ],
  "5": [
    { "date": "2025-12-01", "quantity": 343, "partName": "Part D", "poNumber": "PO-0001" },
    { "date": "2025-12-01", "quantity": 244, "partName": "Part A", "poNumber": "PO-0001" },
    { "date": "2025-12-01", "quantity": 264, "partName": "Part B", "poNumber": "PO-0001" },
    { "date": "2025-12-01", "quantity": 233, "partName": "Part C", "poNumber": "PO-0002" },
    { "date": "2025-12-02", "quantity": 366, "partName": "Part B", "poNumber": "PO-0002" },
    { "date": "2025-12-02", "quantity": 178, "partName": "Part E", "poNumber": "PO-0002" },
    { "date": "2025-12-02", "quantity": 322, "partName": "Part D", "poNumber": "PO-0003" },
    { "date": "2025-12-02", "quantity": 358, "partName": "Part A", "poNumber": "PO-0003" },
    { "date": "2025-12-02", "quantity": 125, "partName": "Part C", "poNumber": "PO-0004" },
    { "date": "2025-12-03", "quantity": 219, "partName": "Part A", "poNumber": "PO-0004" },
    { "date": "2025-12-03", "quantity": 335, "partName": "Part D", "poNumber": "PO-0005" },
    { "date": "2025-12-03", "quantity": 152, "partName": "Part C", "poNumber": "PO-0005" },
    { "date": "2025-12-04", "quantity": 268, "partName": "Part D", "poNumber": "PO-0006" },
    { "date": "2025-12-04", "quantity": 250, "partName": "Part B", "poNumber": "PO-0007" },
    { "date": "2025-12-04", "quantity": 212, "partName": "Part E", "poNumber": "PO-0007" },
    { "date": "2025-12-05", "quantity": 335, "partName": "Part B", "poNumber": "PO-0008" },
    { "date": "2025-12-05", "quantity": 291, "partName": "Part C", "poNumber": "PO-0008" },
    { "date": "2025-12-05", "quantity": 358, "partName": "Part E", "poNumber": "PO-0009" },
    { "date": "2025-12-05", "quantity": 338, "partName": "Part A", "poNumber": "PO-0009" },
    { "date": "2025-12-06", "quantity": 305, "partName": "Part B", "poNumber": "PO-0010" },
    { "date": "2025-12-06", "quantity": 226, "partName": "Part D", "poNumber": "PO-0010" },
    { "date": "2025-12-06", "quantity": 147, "partName": "Part C", "poNumber": "PO-0011" },
    { "date": "2025-12-07", "quantity": 181, "partName": "Part B", "poNumber": "PO-0011" },
    { "date": "2025-12-07", "quantity": 77, "partName": "Part E", "poNumber": "PO-0012" },
    { "date": "2025-12-07", "quantity": 95, "partName": "Part A", "poNumber": "PO-0012" },
    { "date": "2025-12-08", "quantity": 294, "partName": "Part E", "poNumber": "PO-0013" },
    { "date": "2025-12-08", "quantity": 196, "partName": "Part C", "poNumber": "PO-0013" },
    { "date": "2025-12-09", "quantity": 231, "partName": "Part A", "poNumber": "PO-0014" },
    { "date": "2025-12-09", "quantity": 338, "partName": "Part D", "poNumber": "PO-0014" },
    { "date": "2025-12-09", "quantity": 290, "partName": "Part B", "poNumber": "PO-0015" },
    { "date": "2025-12-09", "quantity": 181, "partName": "Part E", "poNumber": "PO-0015" },
    { "date": "2025-12-10", "quantity": 310, "partName": "Part C", "poNumber": "PO-0016" },
    { "date": "2025-12-10", "quantity": 101, "partName": "Part A", "poNumber": "PO-0016" },
    { "date": "2025-12-11", "quantity": 246, "partName": "Part D", "poNumber": "PO-0017" },
    { "date": "2025-12-11", "quantity": 194, "partName": "Part C", "poNumber": "PO-0018" },
    { "date": "2025-12-11", "quantity": 152, "partName": "Part B", "poNumber": "PO-0018" },
    { "date": "2025-12-12", "quantity": 102, "partName": "Part D", "poNumber": "PO-0019" },
    { "date": "2025-12-12", "quantity": 364, "partName": "Part E", "poNumber": "PO-0019" },
    { "date": "2025-12-12", "quantity": 318, "partName": "Part A", "poNumber": "PO-0020" },
    { "date": "2025-12-13", "quantity": 257, "partName": "Part A", "poNumber": "PO-0020" },
    { "date": "2025-12-13", "quantity": 392, "partName": "Part B", "poNumber": "PO-0021" },
    { "date": "2025-12-14", "quantity": 237, "partName": "Part C", "poNumber": "PO-0021" },
    { "date": "2025-12-14", "quantity": 346, "partName": "Part B", "poNumber": "PO-0022" },
    { "date": "2025-12-14", "quantity": 281, "partName": "Part D", "poNumber": "PO-0022" },
    { "date": "2025-12-14", "quantity": 267, "partName": "Part E", "poNumber": "PO-0023" },
    { "date": "2025-12-15", "quantity": 224, "partName": "Part A", "poNumber": "PO-0024" },
    { "date": "2025-12-16", "quantity": 334, "partName": "Part B", "poNumber": "PO-0024" },
    { "date": "2025-12-16", "quantity": 68, "partName": "Part D", "poNumber": "PO-0025" },
    { "date": "2025-12-16", "quantity": 205, "partName": "Part E", "poNumber": "PO-0025" },
    { "date": "2025-12-16", "quantity": 128, "partName": "Part C", "poNumber": "PO-0026" },
    { "date": "2025-12-17", "quantity": 314, "partName": "Part A", "poNumber": "PO-0026" },
    { "date": "2025-12-17", "quantity": 258, "partName": "Part D", "poNumber": "PO-0027" },
    { "date": "2025-12-18", "quantity": 269, "partName": "Part C", "poNumber": "PO-0028" },
    { "date": "2025-12-18", "quantity": 260, "partName": "Part E", "poNumber": "PO-0029" },
    { "date": "2025-12-18", "quantity": 235, "partName": "Part D", "poNumber": "PO-0030" },
    { "date": "2025-12-18", "quantity": 316, "partName": "Part B", "poNumber": "PO-0030" },
    { "date": "2025-12-19", "quantity": 85, "partName": "Part A", "poNumber": "PO-0031" },
    { "date": "2025-12-19", "quantity": 206, "partName": "Part C", "poNumber": "PO-0031" },
    { "date": "2025-12-19", "quantity": 171, "partName": "Part D", "poNumber": "PO-0032" }
  ],
  "6": [
    { "date": "2025-12-01", "quantity": 343, "partName": "Part D", "poNumber": "PO-0001" },
    { "date": "2025-12-01", "quantity": 244, "partName": "Part A", "poNumber": "PO-0001" },
    { "date": "2025-12-01", "quantity": 264, "partName": "Part B", "poNumber": "PO-0001" },
    { "date": "2025-12-01", "quantity": 233, "partName": "Part C", "poNumber": "PO-0002" },
    { "date": "2025-12-02", "quantity": 366, "partName": "Part B", "poNumber": "PO-0002" },
    { "date": "2025-12-02", "quantity": 178, "partName": "Part E", "poNumber": "PO-0002" },
    { "date": "2025-12-02", "quantity": 322, "partName": "Part D", "poNumber": "PO-0003" },
    { "date": "2025-12-02", "quantity": 358, "partName": "Part A", "poNumber": "PO-0003" },
    { "date": "2025-12-02", "quantity": 125, "partName": "Part C", "poNumber": "PO-0004" },
    { "date": "2025-12-03", "quantity": 219, "partName": "Part A", "poNumber": "PO-0004" },
    { "date": "2025-12-03", "quantity": 335, "partName": "Part D", "poNumber": "PO-0005" },
    { "date": "2025-12-03", "quantity": 152, "partName": "Part C", "poNumber": "PO-0005" },
    { "date": "2025-12-04", "quantity": 268, "partName": "Part D", "poNumber": "PO-0006" },
    { "date": "2025-12-04", "quantity": 250, "partName": "Part B", "poNumber": "PO-0007" },
    { "date": "2025-12-04", "quantity": 212, "partName": "Part E", "poNumber": "PO-0007" },
    { "date": "2025-12-05", "quantity": 335, "partName": "Part B", "poNumber": "PO-0008" },
    { "date": "2025-12-05", "quantity": 291, "partName": "Part C", "poNumber": "PO-0008" },
    { "date": "2025-12-05", "quantity": 358, "partName": "Part E", "poNumber": "PO-0009" },
    { "date": "2025-12-05", "quantity": 338, "partName": "Part A", "poNumber": "PO-0009" },
    { "date": "2025-12-06", "quantity": 305, "partName": "Part B", "poNumber": "PO-0010" },
    { "date": "2025-12-06", "quantity": 226, "partName": "Part D", "poNumber": "PO-0010" },
    { "date": "2025-12-06", "quantity": 147, "partName": "Part C", "poNumber": "PO-0011" },
    { "date": "2025-12-07", "quantity": 181, "partName": "Part B", "poNumber": "PO-0011" },
    { "date": "2025-12-07", "quantity": 77, "partName": "Part E", "poNumber": "PO-0012" },
    { "date": "2025-12-07", "quantity": 95, "partName": "Part A", "poNumber": "PO-0012" },
    { "date": "2025-12-08", "quantity": 294, "partName": "Part E", "poNumber": "PO-0013" },
    { "date": "2025-12-08", "quantity": 196, "partName": "Part C", "poNumber": "PO-0013" },
    { "date": "2025-12-09", "quantity": 231, "partName": "Part A", "poNumber": "PO-0014" },
    { "date": "2025-12-09", "quantity": 338, "partName": "Part D", "poNumber": "PO-0014" },
    { "date": "2025-12-09", "quantity": 290, "partName": "Part B", "poNumber": "PO-0015" },
    { "date": "2025-12-09", "quantity": 181, "partName": "Part E", "poNumber": "PO-0015" },
    { "date": "2025-12-10", "quantity": 310, "partName": "Part C", "poNumber": "PO-0016" },
    { "date": "2025-12-10", "quantity": 101, "partName": "Part A", "poNumber": "PO-0016" },
    { "date": "2025-12-11", "quantity": 246, "partName": "Part D", "poNumber": "PO-0017" },
    { "date": "2025-12-11", "quantity": 194, "partName": "Part C", "poNumber": "PO-0018" },
    { "date": "2025-12-11", "quantity": 152, "partName": "Part B", "poNumber": "PO-0018" },
    { "date": "2025-12-12", "quantity": 102, "partName": "Part D", "poNumber": "PO-0019" },
    { "date": "2025-12-12", "quantity": 364, "partName": "Part E", "poNumber": "PO-0019" },
    { "date": "2025-12-12", "quantity": 318, "partName": "Part A", "poNumber": "PO-0020" },
    { "date": "2025-12-13", "quantity": 257, "partName": "Part A", "poNumber": "PO-0020" },
    { "date": "2025-12-13", "quantity": 392, "partName": "Part B", "poNumber": "PO-0021" },
    { "date": "2025-12-14", "quantity": 237, "partName": "Part C", "poNumber": "PO-0021" },
    { "date": "2025-12-14", "quantity": 346, "partName": "Part B", "poNumber": "PO-0022" },
    { "date": "2025-12-14", "quantity": 281, "partName": "Part D", "poNumber": "PO-0022" },
    { "date": "2025-12-14", "quantity": 267, "partName": "Part E", "poNumber": "PO-0023" },
    { "date": "2025-12-15", "quantity": 224, "partName": "Part A", "poNumber": "PO-0024" },
    { "date": "2025-12-16", "quantity": 334, "partName": "Part B", "poNumber": "PO-0024" },
    { "date": "2025-12-16", "quantity": 68, "partName": "Part D", "poNumber": "PO-0025" },
    { "date": "2025-12-16", "quantity": 205, "partName": "Part E", "poNumber": "PO-0025" },
    { "date": "2025-12-16", "quantity": 128, "partName": "Part C", "poNumber": "PO-0026" },
    { "date": "2025-12-17", "quantity": 314, "partName": "Part A", "poNumber": "PO-0026" },
    { "date": "2025-12-17", "quantity": 258, "partName": "Part D", "poNumber": "PO-0027" },
    { "date": "2025-12-18", "quantity": 269, "partName": "Part C", "poNumber": "PO-0028" },
    { "date": "2025-12-18", "quantity": 260, "partName": "Part E", "poNumber": "PO-0029" },
    { "date": "2025-12-18", "quantity": 235, "partName": "Part D", "poNumber": "PO-0030" },
    { "date": "2025-12-18", "quantity": 316, "partName": "Part B", "poNumber": "PO-0030" },
    { "date": "2025-12-19", "quantity": 85, "partName": "Part A", "poNumber": "PO-0031" },
    { "date": "2025-12-19", "quantity": 206, "partName": "Part C", "poNumber": "PO-0031" },
    { "date": "2025-12-19", "quantity": 171, "partName": "Part D", "poNumber": "PO-0032" }
  ],
  "7": [
    { "date": "2025-12-01", "quantity": 343, "partName": "Part D", "poNumber": "PO-0001" },
    { "date": "2025-12-01", "quantity": 244, "partName": "Part A", "poNumber": "PO-0001" },
    { "date": "2025-12-01", "quantity": 264, "partName": "Part B", "poNumber": "PO-0001" },
    { "date": "2025-12-01", "quantity": 233, "partName": "Part C", "poNumber": "PO-0002" },
    { "date": "2025-12-02", "quantity": 366, "partName": "Part B", "poNumber": "PO-0002" },
    { "date": "2025-12-02", "quantity": 178, "partName": "Part E", "poNumber": "PO-0002" },
    { "date": "2025-12-02", "quantity": 322, "partName": "Part D", "poNumber": "PO-0003" },
    { "date": "2025-12-02", "quantity": 358, "partName": "Part A", "poNumber": "PO-0003" },
    { "date": "2025-12-02", "quantity": 125, "partName": "Part C", "poNumber": "PO-0004" },
    { "date": "2025-12-03", "quantity": 219, "partName": "Part A", "poNumber": "PO-0004" },
    { "date": "2025-12-03", "quantity": 335, "partName": "Part D", "poNumber": "PO-0005" },
    { "date": "2025-12-03", "quantity": 152, "partName": "Part C", "poNumber": "PO-0005" },
    { "date": "2025-12-04", "quantity": 268, "partName": "Part D", "poNumber": "PO-0006" },
    { "date": "2025-12-04", "quantity": 250, "partName": "Part B", "poNumber": "PO-0007" },
    { "date": "2025-12-04", "quantity": 212, "partName": "Part E", "poNumber": "PO-0007" },
    { "date": "2025-12-05", "quantity": 335, "partName": "Part B", "poNumber": "PO-0008" },
    { "date": "2025-12-05", "quantity": 291, "partName": "Part C", "poNumber": "PO-0008" },
    { "date": "2025-12-05", "quantity": 358, "partName": "Part E", "poNumber": "PO-0009" },
    { "date": "2025-12-05", "quantity": 338, "partName": "Part A", "poNumber": "PO-0009" },
    { "date": "2025-12-06", "quantity": 305, "partName": "Part B", "poNumber": "PO-0010" },
    { "date": "2025-12-06", "quantity": 226, "partName": "Part D", "poNumber": "PO-0010" },
    { "date": "2025-12-06", "quantity": 147, "partName": "Part C", "poNumber": "PO-0011" },
    { "date": "2025-12-07", "quantity": 181, "partName": "Part B", "poNumber": "PO-0011" },
    { "date": "2025-12-07", "quantity": 77, "partName": "Part E", "poNumber": "PO-0012" },
    { "date": "2025-12-07", "quantity": 95, "partName": "Part A", "poNumber": "PO-0012" },
    { "date": "2025-12-08", "quantity": 294, "partName": "Part E", "poNumber": "PO-0013" },
    { "date": "2025-12-08", "quantity": 196, "partName": "Part C", "poNumber": "PO-0013" },
    { "date": "2025-12-09", "quantity": 231, "partName": "Part A", "poNumber": "PO-0014" },
    { "date": "2025-12-09", "quantity": 338, "partName": "Part D", "poNumber": "PO-0014" },
    { "date": "2025-12-09", "quantity": 290, "partName": "Part B", "poNumber": "PO-0015" },
    { "date": "2025-12-09", "quantity": 181, "partName": "Part E", "poNumber": "PO-0015" },
    { "date": "2025-12-10", "quantity": 310, "partName": "Part C", "poNumber": "PO-0016" },
    { "date": "2025-12-10", "quantity": 101, "partName": "Part A", "poNumber": "PO-0016" },
    { "date": "2025-12-11", "quantity": 246, "partName": "Part D", "poNumber": "PO-0017" },
    { "date": "2025-12-11", "quantity": 194, "partName": "Part C", "poNumber": "PO-0018" },
    { "date": "2025-12-11", "quantity": 152, "partName": "Part B", "poNumber": "PO-0018" },
    { "date": "2025-12-12", "quantity": 102, "partName": "Part D", "poNumber": "PO-0019" },
    { "date": "2025-12-12", "quantity": 364, "partName": "Part E", "poNumber": "PO-0019" },
    { "date": "2025-12-12", "quantity": 318, "partName": "Part A", "poNumber": "PO-0020" },
    { "date": "2025-12-13", "quantity": 257, "partName": "Part A", "poNumber": "PO-0020" },
    { "date": "2025-12-13", "quantity": 392, "partName": "Part B", "poNumber": "PO-0021" },
    { "date": "2025-12-14", "quantity": 237, "partName": "Part C", "poNumber": "PO-0021" },
    { "date": "2025-12-14", "quantity": 346, "partName": "Part B", "poNumber": "PO-0022" },
    { "date": "2025-12-14", "quantity": 281, "partName": "Part D", "poNumber": "PO-0022" },
    { "date": "2025-12-14", "quantity": 267, "partName": "Part E", "poNumber": "PO-0023" },
    { "date": "2025-12-15", "quantity": 224, "partName": "Part A", "poNumber": "PO-0024" },
    { "date": "2025-12-16", "quantity": 334, "partName": "Part B", "poNumber": "PO-0024" },
    { "date": "2025-12-16", "quantity": 68, "partName": "Part D", "poNumber": "PO-0025" },
    { "date": "2025-12-16", "quantity": 205, "partName": "Part E", "poNumber": "PO-0025" },
    { "date": "2025-12-16", "quantity": 128, "partName": "Part C", "poNumber": "PO-0026" },
    { "date": "2025-12-17", "quantity": 314, "partName": "Part A", "poNumber": "PO-0026" },
    { "date": "2025-12-17", "quantity": 258, "partName": "Part D", "poNumber": "PO-0027" },
    { "date": "2025-12-18", "quantity": 269, "partName": "Part C", "poNumber": "PO-0028" },
    { "date": "2025-12-18", "quantity": 260, "partName": "Part E", "poNumber": "PO-0029" },
    { "date": "2025-12-18", "quantity": 235, "partName": "Part D", "poNumber": "PO-0030" },
    { "date": "2025-12-18", "quantity": 316, "partName": "Part B", "poNumber": "PO-0030" },
    { "date": "2025-12-19", "quantity": 85, "partName": "Part A", "poNumber": "PO-0031" },
    { "date": "2025-12-19", "quantity": 206, "partName": "Part C", "poNumber": "PO-0031" },
    { "date": "2025-12-19", "quantity": 171, "partName": "Part D", "poNumber": "PO-0032" }
  ],
  "8": [
    { "date": "2025-12-01", "quantity": 343, "partName": "Part D", "poNumber": "PO-0001" },
    { "date": "2025-12-01", "quantity": 244, "partName": "Part A", "poNumber": "PO-0001" },
    { "date": "2025-12-01", "quantity": 264, "partName": "Part B", "poNumber": "PO-0001" },
    { "date": "2025-12-01", "quantity": 233, "partName": "Part C", "poNumber": "PO-0002" },
    { "date": "2025-12-02", "quantity": 366, "partName": "Part B", "poNumber": "PO-0002" },
    { "date": "2025-12-02", "quantity": 178, "partName": "Part E", "poNumber": "PO-0002" },
    { "date": "2025-12-02", "quantity": 322, "partName": "Part D", "poNumber": "PO-0003" },
    { "date": "2025-12-02", "quantity": 358, "partName": "Part A", "poNumber": "PO-0003" },
    { "date": "2025-12-02", "quantity": 125, "partName": "Part C", "poNumber": "PO-0004" },
    { "date": "2025-12-03", "quantity": 219, "partName": "Part A", "poNumber": "PO-0004" },
    { "date": "2025-12-03", "quantity": 335, "partName": "Part D", "poNumber": "PO-0005" },
    { "date": "2025-12-03", "quantity": 152, "partName": "Part C", "poNumber": "PO-0005" },
    { "date": "2025-12-04", "quantity": 268, "partName": "Part D", "poNumber": "PO-0006" },
    { "date": "2025-12-04", "quantity": 250, "partName": "Part B", "poNumber": "PO-0007" },
    { "date": "2025-12-04", "quantity": 212, "partName": "Part E", "poNumber": "PO-0007" },
    { "date": "2025-12-05", "quantity": 335, "partName": "Part B", "poNumber": "PO-0008" },
    { "date": "2025-12-05", "quantity": 291, "partName": "Part C", "poNumber": "PO-0008" },
    { "date": "2025-12-05", "quantity": 358, "partName": "Part E", "poNumber": "PO-0009" },
    { "date": "2025-12-05", "quantity": 338, "partName": "Part A", "poNumber": "PO-0009" },
    { "date": "2025-12-06", "quantity": 305, "partName": "Part B", "poNumber": "PO-0010" },
    { "date": "2025-12-06", "quantity": 226, "partName": "Part D", "poNumber": "PO-0010" },
    { "date": "2025-12-06", "quantity": 147, "partName": "Part C", "poNumber": "PO-0011" },
    { "date": "2025-12-07", "quantity": 181, "partName": "Part B", "poNumber": "PO-0011" },
    { "date": "2025-12-07", "quantity": 77, "partName": "Part E", "poNumber": "PO-0012" },
    { "date": "2025-12-07", "quantity": 95, "partName": "Part A", "poNumber": "PO-0012" },
    { "date": "2025-12-08", "quantity": 294, "partName": "Part E", "poNumber": "PO-0013" },
    { "date": "2025-12-08", "quantity": 196, "partName": "Part C", "poNumber": "PO-0013" },
    { "date": "2025-12-09", "quantity": 231, "partName": "Part A", "poNumber": "PO-0014" },
    { "date": "2025-12-09", "quantity": 338, "partName": "Part D", "poNumber": "PO-0014" },
    { "date": "2025-12-09", "quantity": 290, "partName": "Part B", "poNumber": "PO-0015" },
    { "date": "2025-12-09", "quantity": 181, "partName": "Part E", "poNumber": "PO-0015" },
    { "date": "2025-12-10", "quantity": 310, "partName": "Part C", "poNumber": "PO-0016" },
    { "date": "2025-12-10", "quantity": 101, "partName": "Part A", "poNumber": "PO-0016" },
    { "date": "2025-12-11", "quantity": 246, "partName": "Part D", "poNumber": "PO-0017" },
    { "date": "2025-12-11", "quantity": 194, "partName": "Part C", "poNumber": "PO-0018" },
    { "date": "2025-12-11", "quantity": 152, "partName": "Part B", "poNumber": "PO-0018" },
    { "date": "2025-12-12", "quantity": 102, "partName": "Part D", "poNumber": "PO-0019" },
    { "date": "2025-12-12", "quantity": 364, "partName": "Part E", "poNumber": "PO-0019" },
    { "date": "2025-12-12", "quantity": 318, "partName": "Part A", "poNumber": "PO-0020" },
    { "date": "2025-12-13", "quantity": 257, "partName": "Part A", "poNumber": "PO-0020" },
    { "date": "2025-12-13", "quantity": 392, "partName": "Part B", "poNumber": "PO-0021" },
    { "date": "2025-12-14", "quantity": 237, "partName": "Part C", "poNumber": "PO-0021" },
    { "date": "2025-12-14", "quantity": 346, "partName": "Part B", "poNumber": "PO-0022" },
    { "date": "2025-12-14", "quantity": 281, "partName": "Part D", "poNumber": "PO-0022" },
    { "date": "2025-12-14", "quantity": 267, "partName": "Part E", "poNumber": "PO-0023" },
    { "date": "2025-12-15", "quantity": 224, "partName": "Part A", "poNumber": "PO-0024" },
    { "date": "2025-12-16", "quantity": 334, "partName": "Part B", "poNumber": "PO-0024" },
    { "date": "2025-12-16", "quantity": 68, "partName": "Part D", "poNumber": "PO-0025" },
    { "date": "2025-12-16", "quantity": 205, "partName": "Part E", "poNumber": "PO-0025" },
    { "date": "2025-12-16", "quantity": 128, "partName": "Part C", "poNumber": "PO-0026" },
    { "date": "2025-12-17", "quantity": 314, "partName": "Part A", "poNumber": "PO-0026" },
    { "date": "2025-12-17", "quantity": 258, "partName": "Part D", "poNumber": "PO-0027" },
    { "date": "2025-12-18", "quantity": 269, "partName": "Part C", "poNumber": "PO-0028" },
    { "date": "2025-12-18", "quantity": 260, "partName": "Part E", "poNumber": "PO-0029" },
    { "date": "2025-12-18", "quantity": 235, "partName": "Part D", "poNumber": "PO-0030" },
    { "date": "2025-12-18", "quantity": 316, "partName": "Part B", "poNumber": "PO-0030" },
    { "date": "2025-12-19", "quantity": 85, "partName": "Part A", "poNumber": "PO-0031" },
    { "date": "2025-12-19", "quantity": 206, "partName": "Part C", "poNumber": "PO-0031" },
    { "date": "2025-12-19", "quantity": 171, "partName": "Part D", "poNumber": "PO-0032" }
  ],
  "9": [
    { "date": "2025-12-01", "quantity": 343, "partName": "Part D", "poNumber": "PO-0001" },
    { "date": "2025-12-01", "quantity": 244, "partName": "Part A", "poNumber": "PO-0001" },
    { "date": "2025-12-01", "quantity": 264, "partName": "Part B", "poNumber": "PO-0001" },
    { "date": "2025-12-01", "quantity": 233, "partName": "Part C", "poNumber": "PO-0002" },
    { "date": "2025-12-02", "quantity": 366, "partName": "Part B", "poNumber": "PO-0002" },
    { "date": "2025-12-02", "quantity": 178, "partName": "Part E", "poNumber": "PO-0002" },
    { "date": "2025-12-02", "quantity": 322, "partName": "Part D", "poNumber": "PO-0003" },
    { "date": "2025-12-02", "quantity": 358, "partName": "Part A", "poNumber": "PO-0003" },
    { "date": "2025-12-02", "quantity": 125, "partName": "Part C", "poNumber": "PO-0004" },
    { "date": "2025-12-03", "quantity": 219, "partName": "Part A", "poNumber": "PO-0004" },
    { "date": "2025-12-03", "quantity": 335, "partName": "Part D", "poNumber": "PO-0005" },
    { "date": "2025-12-03", "quantity": 152, "partName": "Part C", "poNumber": "PO-0005" },
    { "date": "2025-12-04", "quantity": 268, "partName": "Part D", "poNumber": "PO-0006" },
    { "date": "2025-12-04", "quantity": 250, "partName": "Part B", "poNumber": "PO-0007" },
    { "date": "2025-12-04", "quantity": 212, "partName": "Part E", "poNumber": "PO-0007" },
    { "date": "2025-12-05", "quantity": 335, "partName": "Part B", "poNumber": "PO-0008" },
    { "date": "2025-12-05", "quantity": 291, "partName": "Part C", "poNumber": "PO-0008" },
    { "date": "2025-12-05", "quantity": 358, "partName": "Part E", "poNumber": "PO-0009" },
    { "date": "2025-12-05", "quantity": 338, "partName": "Part A", "poNumber": "PO-0009" },
    { "date": "2025-12-06", "quantity": 305, "partName": "Part B", "poNumber": "PO-0010" },
    { "date": "2025-12-06", "quantity": 226, "partName": "Part D", "poNumber": "PO-0010" },
    { "date": "2025-12-06", "quantity": 147, "partName": "Part C", "poNumber": "PO-0011" },
    { "date": "2025-12-07", "quantity": 181, "partName": "Part B", "poNumber": "PO-0011" },
    { "date": "2025-12-07", "quantity": 77, "partName": "Part E", "poNumber": "PO-0012" },
    { "date": "2025-12-07", "quantity": 95, "partName": "Part A", "poNumber": "PO-0012" },
    { "date": "2025-12-08", "quantity": 294, "partName": "Part E", "poNumber": "PO-0013" },
    { "date": "2025-12-08", "quantity": 196, "partName": "Part C", "poNumber": "PO-0013" },
    { "date": "2025-12-09", "quantity": 231, "partName": "Part A", "poNumber": "PO-0014" },
    { "date": "2025-12-09", "quantity": 338, "partName": "Part D", "poNumber": "PO-0014" },
    { "date": "2025-12-09", "quantity": 290, "partName": "Part B", "poNumber": "PO-0015" },
    { "date": "2025-12-09", "quantity": 181, "partName": "Part E", "poNumber": "PO-0015" },
    { "date": "2025-12-10", "quantity": 310, "partName": "Part C", "poNumber": "PO-0016" },
    { "date": "2025-12-10", "quantity": 101, "partName": "Part A", "poNumber": "PO-0016" },
    { "date": "2025-12-11", "quantity": 246, "partName": "Part D", "poNumber": "PO-0017" },
    { "date": "2025-12-11", "quantity": 194, "partName": "Part C", "poNumber": "PO-0018" },
    { "date": "2025-12-11", "quantity": 152, "partName": "Part B", "poNumber": "PO-0018" },
    { "date": "2025-12-12", "quantity": 102, "partName": "Part D", "poNumber": "PO-0019" },
    { "date": "2025-12-12", "quantity": 364, "partName": "Part E", "poNumber": "PO-0019" },
    { "date": "2025-12-12", "quantity": 318, "partName": "Part A", "poNumber": "PO-0020" },
    { "date": "2025-12-13", "quantity": 257, "partName": "Part A", "poNumber": "PO-0020" },
    { "date": "2025-12-13", "quantity": 392, "partName": "Part B", "poNumber": "PO-0021" },
    { "date": "2025-12-14", "quantity": 237, "partName": "Part C", "poNumber": "PO-0021" },
    { "date": "2025-12-14", "quantity": 346, "partName": "Part B", "poNumber": "PO-0022" },
    { "date": "2025-12-14", "quantity": 281, "partName": "Part D", "poNumber": "PO-0022" },
    { "date": "2025-12-14", "quantity": 267, "partName": "Part E", "poNumber": "PO-0023" },
    { "date": "2025-12-15", "quantity": 224, "partName": "Part A", "poNumber": "PO-0024" },
    { "date": "2025-12-16", "quantity": 334, "partName": "Part B", "poNumber": "PO-0024" },
    { "date": "2025-12-16", "quantity": 68, "partName": "Part D", "poNumber": "PO-0025" },
    { "date": "2025-12-16", "quantity": 205, "partName": "Part E", "poNumber": "PO-0025" },
    { "date": "2025-12-16", "quantity": 128, "partName": "Part C", "poNumber": "PO-0026" },
    { "date": "2025-12-17", "quantity": 314, "partName": "Part A", "poNumber": "PO-0026" },
    { "date": "2025-12-17", "quantity": 258, "partName": "Part D", "poNumber": "PO-0027" },
    { "date": "2025-12-18", "quantity": 269, "partName": "Part C", "poNumber": "PO-0028" },
    { "date": "2025-12-18", "quantity": 260, "partName": "Part E", "poNumber": "PO-0029" },
    { "date": "2025-12-18", "quantity": 235, "partName": "Part D", "poNumber": "PO-0030" },
    { "date": "2025-12-18", "quantity": 316, "partName": "Part B", "poNumber": "PO-0030" },
    { "date": "2025-12-19", "quantity": 85, "partName": "Part A", "poNumber": "PO-0031" },
    { "date": "2025-12-19", "quantity": 206, "partName": "Part C", "poNumber": "PO-0031" },
    { "date": "2025-12-19", "quantity": 171, "partName": "Part D", "poNumber": "PO-0032" }
  ],
  "10": [
    { "date": "2025-12-01", "quantity": 343, "partName": "Part D", "poNumber": "PO-0001" },
    { "date": "2025-12-01", "quantity": 244, "partName": "Part A", "poNumber": "PO-0001" },
    { "date": "2025-12-01", "quantity": 264, "partName": "Part B", "poNumber": "PO-0001" },
    { "date": "2025-12-01", "quantity": 233, "partName": "Part C", "poNumber": "PO-0002" },
    { "date": "2025-12-02", "quantity": 366, "partName": "Part B", "poNumber": "PO-0002" },
    { "date": "2025-12-02", "quantity": 178, "partName": "Part E", "poNumber": "PO-0002" },
    { "date": "2025-12-02", "quantity": 322, "partName": "Part D", "poNumber": "PO-0003" },
    { "date": "2025-12-02", "quantity": 358, "partName": "Part A", "poNumber": "PO-0003" },
    { "date": "2025-12-02", "quantity": 125, "partName": "Part C", "poNumber": "PO-0004" },
    { "date": "2025-12-03", "quantity": 219, "partName": "Part A", "poNumber": "PO-0004" },
    { "date": "2025-12-03", "quantity": 335, "partName": "Part D", "poNumber": "PO-0005" },
    { "date": "2025-12-03", "quantity": 152, "partName": "Part C", "poNumber": "PO-0005" },
    { "date": "2025-12-04", "quantity": 268, "partName": "Part D", "poNumber": "PO-0006" },
    { "date": "2025-12-04", "quantity": 250, "partName": "Part B", "poNumber": "PO-0007" },
    { "date": "2025-12-04", "quantity": 212, "partName": "Part E", "poNumber": "PO-0007" },
    { "date": "2025-12-05", "quantity": 335, "partName": "Part B", "poNumber": "PO-0008" },
    { "date": "2025-12-05", "quantity": 291, "partName": "Part C", "poNumber": "PO-0008" },
    { "date": "2025-12-05", "quantity": 358, "partName": "Part E", "poNumber": "PO-0009" },
    { "date": "2025-12-05", "quantity": 338, "partName": "Part A", "poNumber": "PO-0009" },
    { "date": "2025-12-06", "quantity": 305, "partName": "Part B", "poNumber": "PO-0010" },
    { "date": "2025-12-06", "quantity": 226, "partName": "Part D", "poNumber": "PO-0010" },
    { "date": "2025-12-06", "quantity": 147, "partName": "Part C", "poNumber": "PO-0011" },
    { "date": "2025-12-07", "quantity": 181, "partName": "Part B", "poNumber": "PO-0011" },
    { "date": "2025-12-07", "quantity": 77, "partName": "Part E", "poNumber": "PO-0012" },
    { "date": "2025-12-07", "quantity": 95, "partName": "Part A", "poNumber": "PO-0012" },
    { "date": "2025-12-08", "quantity": 294, "partName": "Part E", "poNumber": "PO-0013" },
    { "date": "2025-12-08", "quantity": 196, "partName": "Part C", "poNumber": "PO-0013" },
    { "date": "2025-12-09", "quantity": 231, "partName": "Part A", "poNumber": "PO-0014" },
    { "date": "2025-12-09", "quantity": 338, "partName": "Part D", "poNumber": "PO-0014" },
    { "date": "2025-12-09", "quantity": 290, "partName": "Part B", "poNumber": "PO-0015" },
    { "date": "2025-12-09", "quantity": 181, "partName": "Part E", "poNumber": "PO-0015" },
    { "date": "2025-12-10", "quantity": 310, "partName": "Part C", "poNumber": "PO-0016" },
    { "date": "2025-12-10", "quantity": 101, "partName": "Part A", "poNumber": "PO-0016" },
    { "date": "2025-12-11", "quantity": 246, "partName": "Part D", "poNumber": "PO-0017" },
    { "date": "2025-12-11", "quantity": 194, "partName": "Part C", "poNumber": "PO-0018" },
    { "date": "2025-12-11", "quantity": 152, "partName": "Part B", "poNumber": "PO-0018" },
    { "date": "2025-12-12", "quantity": 102, "partName": "Part D", "poNumber": "PO-0019" },
    { "date": "2025-12-12", "quantity": 364, "partName": "Part E", "poNumber": "PO-0019" },
    { "date": "2025-12-12", "quantity": 318, "partName": "Part A", "poNumber": "PO-0020" },
    { "date": "2025-12-13", "quantity": 257, "partName": "Part A", "poNumber": "PO-0020" },
    { "date": "2025-12-13", "quantity": 392, "partName": "Part B", "poNumber": "PO-0021" },
    { "date": "2025-12-14", "quantity": 237, "partName": "Part C", "poNumber": "PO-0021" },
    { "date": "2025-12-14", "quantity": 346, "partName": "Part B", "poNumber": "PO-0022" },
    { "date": "2025-12-14", "quantity": 281, "partName": "Part D", "poNumber": "PO-0022" },
    { "date": "2025-12-14", "quantity": 267, "partName": "Part E", "poNumber": "PO-0023" },
    { "date": "2025-12-15", "quantity": 224, "partName": "Part A", "poNumber": "PO-0024" },
    { "date": "2025-12-16", "quantity": 334, "partName": "Part B", "poNumber": "PO-0024" },
    { "date": "2025-12-16", "quantity": 68, "partName": "Part D", "poNumber": "PO-0025" },
    { "date": "2025-12-16", "quantity": 205, "partName": "Part E", "poNumber": "PO-0025" },
    { "date": "2025-12-16", "quantity": 128, "partName": "Part C", "poNumber": "PO-0026" },
    { "date": "2025-12-17", "quantity": 314, "partName": "Part A", "poNumber": "PO-0026" },
    { "date": "2025-12-17", "quantity": 258, "partName": "Part D", "poNumber": "PO-0027" },
    { "date": "2025-12-18", "quantity": 269, "partName": "Part C", "poNumber": "PO-0028" },
    { "date": "2025-12-18", "quantity": 260, "partName": "Part E", "poNumber": "PO-0029" },
    { "date": "2025-12-18", "quantity": 235, "partName": "Part D", "poNumber": "PO-0030" },
    { "date": "2025-12-18", "quantity": 316, "partName": "Part B", "poNumber": "PO-0030" },
    { "date": "2025-12-19", "quantity": 85, "partName": "Part A", "poNumber": "PO-0031" },
    { "date": "2025-12-19", "quantity": 206, "partName": "Part C", "poNumber": "PO-0031" },
    { "date": "2025-12-19", "quantity": 171, "partName": "Part D", "poNumber": "PO-0032" }
  ]
}
